selfhealing/__init__.py
selfhealing/listener.py
web_sre_engine-0.1.0.dist-info/licenses/LICENSE
web_sre_engine-0.1.0.dist-info/METADATA
web_sre_engine-0.1.0.dist-info/WHEEL
web_sre_engine-0.1.0.dist-info/top_level.txt
web_sre_engine-0.1.0.dist-info/RECORD
