Metadata-Version: 2.4
Name: web_SRE_ENGINE
Version: 0.1.0
Summary: AI-powered self-healing web locator listener for Robot Framework
Author: Abhilesh Thakuria
Requires-Python: >=3.8
License-File: LICENSE
Requires-Dist: robotframework>=6.0
Requires-Dist: robotframework-seleniumlibrary>=6.0
Requires-Dist: selenium>=4.10
Requires-Dist: pyyaml
Requires-Dist: beautifulsoup4
Requires-Dist: python-dotenv
Requires-Dist: openai>=1.0
Dynamic: license-file
